legend_testdata/__init__.py
legend_testdata/_version.py
legend_testdata/core.py
legend_testdata-0.4.3.dist-info/LICENSE
legend_testdata-0.4.3.dist-info/METADATA
legend_testdata-0.4.3.dist-info/WHEEL
legend_testdata-0.4.3.dist-info/top_level.txt
legend_testdata-0.4.3.dist-info/RECORD
