Metadata-Version: 2.1
Name: legend-testdata
Version: 0.4.3
Summary: Python package for accessing LEGEND test data
Home-page: https://github.com/legend-exp/pylegendtestdata
Author: The LEGEND collaboration
Maintainer: The LEGEND collaboration
License: MIT
Classifier: Development Status :: 4 - Beta
Classifier: Intended Audience :: Developers
Classifier: Intended Audience :: Information Technology
Classifier: Intended Audience :: Science/Research
Classifier: License :: OSI Approved :: MIT License
Classifier: Operating System :: MacOS
Classifier: Operating System :: POSIX
Classifier: Operating System :: Unix
Classifier: Programming Language :: Python
Classifier: Programming Language :: Python :: 3
Classifier: Programming Language :: Python :: 3 :: Only
Classifier: Topic :: Scientific/Engineering
Classifier: Topic :: Scientific/Engineering :: Information Analysis
Classifier: Topic :: Scientific/Engineering :: Mathematics
Classifier: Topic :: Scientific/Engineering :: Physics
Classifier: Topic :: Software Development
Requires-Python: >=3.7
License-File: LICENSE
Requires-Dist: GitPython
Provides-Extra: test
Requires-Dist: pre-commit ; extra == 'test'
Requires-Dist: pytest (>=6.0) ; extra == 'test'
Requires-Dist: pytest-cov ; extra == 'test'
